looprmsd/__init__.py
looprmsd/loop_rmsd_antibody.py
looprmsd/dat/1bj1.pdb
looprmsd/dat/1bj1_HL_H3_pred.pdb
looprmsd-0.1.6.dist-info/LICENCE
looprmsd-0.1.6.dist-info/METADATA
looprmsd-0.1.6.dist-info/WHEEL
looprmsd-0.1.6.dist-info/top_level.txt
looprmsd-0.1.6.dist-info/RECORD
