Metadata-Version: 2.1
Name: looprmsd
Version: 0.1.6
Summary: LoopRMSD is a Python package for calculating the RMSD of a loop region given two pdbs
Home-page: https://github.com/Galux-Inc/loopRMSD
Author: Jeffrey Lim
Author-email: js.lim@galux.co.kr
License-File: LICENCE
Requires-Dist: numpy
